shs_calculator/__init__.py
shs_calculator/calculator.py
shs_calculator/cli.py
shs_calculator-0.1.3.dist-info/licenses/LICENSE
shs_calculator-0.1.3.dist-info/METADATA
shs_calculator-0.1.3.dist-info/WHEEL
shs_calculator-0.1.3.dist-info/entry_points.txt
shs_calculator-0.1.3.dist-info/top_level.txt
shs_calculator-0.1.3.dist-info/RECORD
