Metadata-Version: 2.4
Name: shs_calculator
Version: 0.1.3
Summary: 一个简单的加减乘除计算包，完美演绎了Python包的应用过程。
Author-email: Hollson <hollson@qq.com>
License-Expression: MIT
Project-URL: Homepage, https://github.com/hollson/shs_calculator
Keywords: calculator,python-beginner
Classifier: Programming Language :: Python :: 3
Classifier: Operating System :: OS Independent
Classifier: Intended Audience :: Developers
Classifier: Topic :: Education
Classifier: Topic :: Software Development :: Testing
Requires-Python: >=3.12
License-File: LICENSE
Dynamic: license-file
